<?xml version="1.0" encoding="UTF-8" standalone="no"?>
<?xml-stylesheet type="text/xsl" href="pdfcard.xsl"?><pdfcard>
<pdf_data ApplicationName="PDF-4+ 2020" ApplicationVersion="4.20.0.1" CurrentYear="2019">
<pdf_number>04-009-0515</pdf_number>
<chemical_formula>V2 Mn2 O7</chemical_formula>
<empirical_formula>Mn2 O7 V2</empirical_formula>
<anx>A2B2X7</anx>
<chemical_name>Vanadium Manganese Oxide</chemical_name>
<xstal_system>Triclinic (Anorthic)</xstal_system>
<xtldx>3.792</xtldx>
<ds>3.79</ds>
<lpf_rep_struc>V2 Mn2 O7,aP44,2</lpf_rep_struc>
<lpf_rep_struc_alpha_order>Mn2 O7 V2,aP44,2</lpf_rep_struc_alpha_order>
<pressure_temperature>Ambient</pressure_temperature>
<status>Alternate</status>
<cell_a>6.879(2)</cell_a>
<cell_b>7.973(2)</cell_b>
<cell_c>10.948(3)</cell_c>
<cell_alpha>87.92(3)</cell_alpha>
<cell_beta>72.00(2)</cell_beta>
<cell_gamma>83.29(3)</cell_gamma>
<z>4.00</z>
<cell_vol>567.16</cell_vol>
<cell_mv>141.79</cell_mv>
<authcovera>1.592</authcovera>
<authaoverb>0.863</authaoverb>
<authcoverb>1.373</authcoverb>
<xtlvol>567.16</xtlvol>
<redcellvol>567.16</redcellvol>
<xtla>7.973</xtla>
<xtlb>10.948</xtlb>
<xtlc>6.879</xtlc>
<xtlal>108.00</xtlal>
<xtlbe>96.71</xtlbe>
<xtlga>87.92</xtlga>
<xtlcovera>0.863</xtlcovera>
<xtlaoverb>0.728</xtlaoverb>
<xtlcoverb>0.628</xtlcoverb>
<redcell_a>6.879</redcell_a>
<redcell_b>7.973</redcell_b>
<redcell_c>10.948</redcell_c>
<redcell_al>87.92</redcell_al>
<redcell_be>72.00</redcell_be>
<redcell_ga>83.29</redcell_ga>
<xtlz>4.00</xtlz>
<ss>F(30) = 102.5(0.0054, 54)</ss>
<xtlsg>P-1 (2)</xtlsg>
<xtlmolwt>323.75</xtlmolwt>
<quality_mark>Prototyping</quality_mark>
<iic>1.26</iic>
<iic_nd>0.12</iic_nd>
<lambda>1.5406</lambda>
<patrad>CuKα1</patrad>
<source>Calculated - Peak</source>
<instrument>Calculated</instrument>
<temperature>298.0</temperature>
<aspectn>2</aspectn>
<spgr_label>Space Group</spgr_label>
<spgr>P-1 (2)</spgr>
<pearson>aP44.00</pearson>
<entry_date>09/01/2006</entry_date>
<last_mod_date>09/01/2015</last_mod_date>
<last_modifications>Add unit cell precision</last_modifications>
<weight_percent>Mn33.94 O34.59 V31.47</weight_percent>
<atomic_percent>Mn18.18 O63.64 V18.18</atomic_percent>
<sg_sym_ops>
<sg_sym_op>
<seq>1</seq>
<operator>x,y,z</operator>
</sg_sym_op>
<sg_sym_op>
<seq>2</seq>
<operator>-x,-y,-z</operator>
</sg_sym_op>
</sg_sym_ops>
<idp_column>IDP</idp_column>
<adp_column>ADP</adp_column>
<atomic_coords>
<atomic_coord>
<atom>O</atom>
<num>1</num>
<wyckoff>2i</wyckoff>
<symmetry>1</symmetry>
<x>0.0094</x>
<y>0.0189</y>
<z>0.7533</z>
<sof>1.0</sof>
<aet>2#a</aet>
</atomic_coord>
<atomic_coord>
<atom>O</atom>
<num>2</num>
<wyckoff>2i</wyckoff>
<symmetry>1</symmetry>
<x>0.0468</x>
<y>0.3559</y>
<z>0.7052</z>
<sof>1.0</sof>
<aet>3#a</aet>
</atomic_coord>
<atomic_coord>
<atom>O</atom>
<num>3</num>
<wyckoff>2i</wyckoff>
<symmetry>1</symmetry>
<x>0.0532</x>
<y>0.321</y>
<z>0.2135</z>
<sof>1.0</sof>
<aet>1#a</aet>
</atomic_coord>
<atomic_coord>
<atom>V</atom>
<num>4</num>
<wyckoff>2i</wyckoff>
<symmetry>1</symmetry>
<x>0.0657</x>
<y>0.1461</y>
<z>0.1298</z>
<sof>1.0</sof>
<aet>4-a</aet>
</atomic_coord>
<atomic_coord>
<atom>V</atom>
<num>5</num>
<wyckoff>2i</wyckoff>
<symmetry>1</symmetry>
<x>0.0673</x>
<y>0.1684</y>
<z>0.6331</z>
<sof>1.0</sof>
<aet>4-a</aet>
</atomic_coord>
<atomic_coord>
<atom>Mn</atom>
<num>6</num>
<wyckoff>2i</wyckoff>
<symmetry>1</symmetry>
<x>0.083</x>
<y>0.5966</y>
<z>0.098</z>
<sof>1.0</sof>
<aet>6-a</aet>
</atomic_coord>
<atomic_coord>
<atom>O</atom>
<num>7</num>
<wyckoff>2i</wyckoff>
<symmetry>1</symmetry>
<x>0.0964</x>
<y>0.8177</y>
<z>0.4566</z>
<sof>1.0</sof>
<aet>3#a</aet>
</atomic_coord>
<atomic_coord>
<atom>Mn</atom>
<num>8</num>
<wyckoff>2i</wyckoff>
<symmetry>1</symmetry>
<x>0.0986</x>
<y>0.5943</y>
<z>0.594</z>
<sof>1.0</sof>
<aet>6-a</aet>
</atomic_coord>
<atomic_coord>
<atom>O</atom>
<num>9</num>
<wyckoff>2i</wyckoff>
<symmetry>1</symmetry>
<x>0.2012</x>
<y>0.4112</y>
<z>0.4353</z>
<sof>1.0</sof>
<aet>3#a</aet>
</atomic_coord>
<atomic_coord>
<atom>O</atom>
<num>10</num>
<wyckoff>2i</wyckoff>
<symmetry>1</symmetry>
<x>0.3112</x>
<y>0.0845</y>
<z>0.0359</z>
<sof>1.0</sof>
<aet>3#a</aet>
</atomic_coord>
<atomic_coord>
<atom>O</atom>
<num>11</num>
<wyckoff>2i</wyckoff>
<symmetry>1</symmetry>
<x>0.3174</x>
<y>0.1101</y>
<z>0.5387</z>
<sof>1.0</sof>
<aet>1#a</aet>
</atomic_coord>
<atomic_coord>
<atom>O</atom>
<num>12</num>
<wyckoff>2i</wyckoff>
<symmetry>1</symmetry>
<x>0.3773</x>
<y>0.6716</y>
<z>0.0731</z>
<sof>1.0</sof>
<aet>3#a</aet>
</atomic_coord>
<atomic_coord>
<atom>V</atom>
<num>13</num>
<wyckoff>2i</wyckoff>
<symmetry>1</symmetry>
<x>0.4256</x>
<y>0.2868</y>
<z>0.3592</z>
<sof>1.0</sof>
<aet>4-a</aet>
</atomic_coord>
<atomic_coord>
<atom>O</atom>
<num>14</num>
<wyckoff>2i</wyckoff>
<symmetry>1</symmetry>
<x>0.4372</x>
<y>0.095</y>
<z>0.2876</z>
<sof>1.0</sof>
<aet>1#a</aet>
</atomic_coord>
<atomic_coord>
<atom>O</atom>
<num>15</num>
<wyckoff>2i</wyckoff>
<symmetry>1</symmetry>
<x>0.4746</x>
<y>0.2908</y>
<z>0.7238</z>
<sof>1.0</sof>
<aet>2#a</aet>
</atomic_coord>
<atomic_coord>
<atom>O</atom>
<num>16</num>
<wyckoff>2i</wyckoff>
<symmetry>1</symmetry>
<x>0.503</x>
<y>0.3851</y>
<z>0.2023</z>
<sof>1.0</sof>
<aet>2#a</aet>
</atomic_coord>
<atomic_coord>
<atom>V</atom>
<num>17</num>
<wyckoff>2i</wyckoff>
<symmetry>1</symmetry>
<x>0.5538</x>
<y>0.5954</y>
<z>0.1498</z>
<sof>1.0</sof>
<aet>4-a</aet>
</atomic_coord>
<atomic_coord>
<atom>Mn</atom>
<num>18</num>
<wyckoff>2i</wyckoff>
<symmetry>1</symmetry>
<x>0.5799</x>
<y>0.1428</y>
<z>0.0792</z>
<sof>1.0</sof>
<aet>6-a</aet>
</atomic_coord>
<atomic_coord>
<atom>Mn</atom>
<num>19</num>
<wyckoff>2i</wyckoff>
<symmetry>1</symmetry>
<x>0.6034</x>
<y>0.1137</y>
<z>0.5838</z>
<sof>1.0</sof>
<aet>6-a</aet>
</atomic_coord>
<atomic_coord>
<atom>O</atom>
<num>20</num>
<wyckoff>2i</wyckoff>
<symmetry>1</symmetry>
<x>0.6194</x>
<y>0.3075</y>
<z>0.4196</z>
<sof>1.0</sof>
<aet>1#a</aet>
</atomic_coord>
<atomic_coord>
<atom>O</atom>
<num>21</num>
<wyckoff>2i</wyckoff>
<symmetry>1</symmetry>
<x>0.8059</x>
<y>0.5799</y>
<z>0.0546</z>
<sof>1.0</sof>
<aet>3#a</aet>
</atomic_coord>
<atomic_coord>
<atom>O</atom>
<num>22</num>
<wyckoff>2i</wyckoff>
<symmetry>1</symmetry>
<x>0.9004</x>
<y>0.1778</y>
<z>0.0432</z>
<sof>1.0</sof>
<aet>1#a</aet>
</atomic_coord>
</atomic_coords>
<ani_temp_facs/>
<ac_space_group>P-1 (2)</ac_space_group>
<ac_unit_cell_a>6.879</ac_unit_cell_a>
<ac_unit_cell_b>7.973</ac_unit_cell_b>
<ac_unit_cell_c>10.948</ac_unit_cell_c>
<ac_unit_cell_alpha>87.92</ac_unit_cell_alpha>
<ac_unit_cell_beta>72</ac_unit_cell_beta>
<ac_unit_cell_gamma>83.29</ac_unit_cell_gamma>
<subfile_indicator>Inorganic</subfile_indicator>
<cross_ref_pdf_numbers>00-047-0342 (Primary), 00-052-1265 (Primary), 04-009-0571 (Alternate), 04-010-0727 (Primary)</cross_ref_pdf_numbers>
<references>
<reference_group>
<type>Primary Reference</type>
<reference>Calculated from LPF using POWD-12++.</reference>
</reference_group>
<reference_group>
<type>Structure</type>
<reference>Surat L.L., Velikodnyi Y.A., Zhuravlev V.D. "The Mn2V2O7-β-Mg2V2O7 system". Russ. J. Inorg. Chem. (Engl. Transl.) 1991, 36, 1058.</reference>
</reference_group>
</references>
<database_comments>ANX: A2B2X7. LPF Collection Code: 542916. Polymorphism: Room temperature phase. Unit Cell Data Source: Powder Diffraction.</database_comments>
<crystal_properties>Centrosymmetric</crystal_properties>
<phase>Room temperature phase.</phase>
</pdf_data>
<graphs>
<wave_length>Cu Kα1 1.54056 Å</wave_length>
<chart_name>PDF Card - 04-009-0515.jpg</chart_name>
<stick_series type="V2 Mn2 O7 - 04-009-0515 (Stick, Fixed Slit Intensity)">
<intensity>
<theta>8.485</theta>
<da>10.41220</da>
<intensity>1</intensity>
<h>0</h>
<k>0</k>
<l>1</l>
<F/>
</intensity>
<intensity>
<theta>11.165</theta>
<da>7.91839</da>
<intensity>11</intensity>
<h>0</h>
<k>1</k>
<l>0</l>
<F/>
</intensity>
<intensity>
<theta>13.652</theta>
<da>6.48102</da>
<intensity>2m</intensity>
<h>1</h>
<k>0</k>
<l>0</l>
<F/>
</intensity>
<intensity>
<theta>13.652</theta>
<da>6.48102</da>
<intensity>2m</intensity>
<h>1</h>
<k>0</k>
<l>1</l>
<F/>
</intensity>
<intensity>
<theta>14.038</theta>
<da>6.30343</da>
<intensity>36m</intensity>
<h>0</h>
<k>1</k>
<l>1</l>
<F/>
</intensity>
<intensity>
<theta>14.038</theta>
<da>6.30343</da>
<intensity>36m</intensity>
<h>0</h>
<k>-1</k>
<l>1</l>
<F/>
</intensity>
<intensity>
<theta>16.674</theta>
<da>5.31239</da>
<intensity>39m</intensity>
<h>1</h>
<k>1</k>
<l>0</l>
<F/>
</intensity>
<intensity>
<theta>16.674</theta>
<da>5.31239</da>
<intensity>39m</intensity>
<h>1</h>
<k>1</k>
<l>1</l>
<F/>
</intensity>
<intensity>
<theta>17.017</theta>
<da>5.20608</da>
<intensity>73</intensity>
<h>0</h>
<k>0</k>
<l>2</l>
<F/>
</intensity>
<intensity>
<theta>18.155</theta>
<da>4.88231</da>
<intensity>1</intensity>
<h>-1</h>
<k>0</k>
<l>1</l>
<F/>
</intensity>
<intensity>
<theta>18.254</theta>
<da>4.85601</da>
<intensity>1</intensity>
<h>1</h>
<k>0</k>
<l>2</l>
<F/>
</intensity>
<intensity>
<theta>18.580</theta>
<da>4.77156</da>
<intensity>15m</intensity>
<h>1</h>
<k>-1</k>
<l>1</l>
<F/>
</intensity>
<intensity>
<theta>18.580</theta>
<da>4.77156</da>
<intensity>15m</intensity>
<h>-1</h>
<k>1</k>
<l>0</l>
<F/>
</intensity>
<intensity>
<theta>20.400</theta>
<da>4.34971</da>
<intensity>25m</intensity>
<h>0</h>
<k>1</k>
<l>2</l>
<F/>
</intensity>
<intensity>
<theta>20.400</theta>
<da>4.34971</da>
<intensity>25m</intensity>
<h>0</h>
<k>-1</k>
<l>2</l>
<F/>
</intensity>
<intensity>
<theta>20.628</theta>
<da>4.30216</da>
<intensity>44</intensity>
<h>1</h>
<k>1</k>
<l>2</l>
<F/>
</intensity>
<intensity>
<theta>22.154</theta>
<da>4.00922</da>
<intensity>29</intensity>
<h>-1</h>
<k>1</k>
<l>1</l>
<F/>
</intensity>
<intensity>
<theta>22.239</theta>
<da>3.99415</da>
<intensity>17</intensity>
<h>1</h>
<k>-1</k>
<l>2</l>
<F/>
</intensity>
<intensity>
<theta>22.437</theta>
<da>3.95919</da>
<intensity>19</intensity>
<h>0</h>
<k>2</k>
<l>0</l>
<F/>
</intensity>
<intensity>
<theta>24.029</theta>
<da>3.70044</da>
<intensity>27m</intensity>
<h>0</h>
<k>2</k>
<l>1</l>
<F/>
</intensity>
<intensity>
<theta>24.029</theta>
<da>3.70044</da>
<intensity>27m</intensity>
<h>0</h>
<k>-2</k>
<l>1</l>
<F/>
</intensity>
<intensity>
<theta>24.978</theta>
<da>3.56199</da>
<intensity>5m</intensity>
<h>1</h>
<k>2</k>
<l>0</l>
<F/>
</intensity>
<intensity>
<theta>24.978</theta>
<da>3.56199</da>
<intensity>5m</intensity>
<h>1</h>
<k>2</k>
<l>1</l>
<F/>
</intensity>
<intensity>
<theta>25.646</theta>
<da>3.47072</da>
<intensity>1</intensity>
<h>0</h>
<k>0</k>
<l>3</l>
<F/>
</intensity>
<intensity>
<theta>26.064</theta>
<da>3.41589</da>
<intensity>8</intensity>
<h>2</h>
<k>0</k>
<l>1</l>
<F/>
</intensity>
<intensity>
<theta>26.883</theta>
<da>3.31366</da>
<intensity>14</intensity>
<h>1</h>
<k>1</k>
<l>3</l>
<F/>
</intensity>
<intensity>
<theta>27.413</theta>
<da>3.25089</da>
<intensity>358</intensity>
<h>2</h>
<k>0</k>
<l>0</l>
<F/>
</intensity>
<intensity>
<theta>27.502</theta>
<da>3.24051</da>
<intensity>529</intensity>
<h>2</h>
<k>0</k>
<l>2</l>
<F/>
</intensity>
<intensity>
<theta>27.779</theta>
<da>3.20880</da>
<intensity>28m</intensity>
<h>1</h>
<k>2</k>
<l>2</l>
<F/>
</intensity>
<intensity>
<theta>27.779</theta>
<da>3.20880</da>
<intensity>28m</intensity>
<h>-1</h>
<k>-2</k>
<l>1</l>
<F/>
</intensity>
<intensity>
<theta>28.045</theta>
<da>3.17898</da>
<intensity>238m</intensity>
<h>0</h>
<k>-1</k>
<l>3</l>
<F/>
</intensity>
<intensity>
<theta>28.045</theta>
<da>3.17898</da>
<intensity>238m</intensity>
<h>-1</h>
<k>1</k>
<l>2</l>
<F/>
</intensity>
<intensity>
<theta>28.298</theta>
<da>3.15111</da>
<intensity>1000m</intensity>
<h>0</h>
<k>2</k>
<l>2</l>
<F/>
</intensity>
<intensity>
<theta>28.298</theta>
<da>3.15111</da>
<intensity>1000m</intensity>
<h>0</h>
<k>-2</k>
<l>2</l>
<F/>
</intensity>
<intensity>
<theta>29.643</theta>
<da>3.01114</da>
<intensity>5</intensity>
<h>2</h>
<k>-1</k>
<l>1</l>
<F/>
</intensity>
<intensity>
<theta>30.199</theta>
<da>2.95693</da>
<intensity>1</intensity>
<h>-1</h>
<k>2</k>
<l>1</l>
<F/>
</intensity>
<intensity>
<theta>30.265</theta>
<da>2.95068</da>
<intensity>1</intensity>
<h>1</h>
<k>-2</k>
<l>2</l>
<F/>
</intensity>
<intensity>
<theta>30.928</theta>
<da>2.88888</da>
<intensity>11</intensity>
<h>2</h>
<k>-1</k>
<l>2</l>
<F/>
</intensity>
<intensity>
<theta>32.161</theta>
<da>2.78090</da>
<intensity>9</intensity>
<h>-2</h>
<k>-1</k>
<l>1</l>
<F/>
</intensity>
<intensity>
<theta>32.314</theta>
<da>2.76813</da>
<intensity>2</intensity>
<h>2</h>
<k>1</k>
<l>3</l>
<F/>
</intensity>
<intensity>
<theta>32.531</theta>
<da>2.75014</da>
<intensity>3</intensity>
<h>2</h>
<k>2</k>
<l>1</l>
<F/>
</intensity>
<intensity>
<theta>32.740</theta>
<da>2.73306</da>
<intensity>3m</intensity>
<h>-1</h>
<k>0</k>
<l>3</l>
<F/>
</intensity>
<intensity>
<theta>32.740</theta>
<da>2.73306</da>
<intensity>3m</intensity>
<h>-1</h>
<k>-2</k>
<l>2</l>
<F/>
</intensity>
<intensity>
<theta>32.829</theta>
<da>2.72584</da>
<intensity>3m</intensity>
<h>1</h>
<k>0</k>
<l>4</l>
<F/>
</intensity>
<intensity>
<theta>32.829</theta>
<da>2.72584</da>
<intensity>3m</intensity>
<h>1</h>
<k>2</k>
<l>3</l>
<F/>
</intensity>
<intensity>
<theta>33.643</theta>
<da>2.66172</da>
<intensity>139m</intensity>
<h>2</h>
<k>2</k>
<l>0</l>
<F/>
</intensity>
<intensity>
<theta>33.643</theta>
<da>2.66172</da>
<intensity>139m</intensity>
<h>2</h>
<k>2</k>
<l>2</l>
<F/>
</intensity>
<intensity>
<theta>33.935</theta>
<da>2.63946</da>
<intensity>10</intensity>
<h>0</h>
<k>3</k>
<l>0</l>
<F/>
</intensity>
<intensity>
<theta>34.178</theta>
<da>2.62131</da>
<intensity>19</intensity>
<h>-1</h>
<k>-1</k>
<l>3</l>
<F/>
</intensity>
<intensity>
<theta>34.302</theta>
<da>2.61209</da>
<intensity>70m</intensity>
<h>0</h>
<k>-2</k>
<l>3</l>
<F/>
</intensity>
<intensity>
<theta>34.302</theta>
<da>2.61209</da>
<intensity>70m</intensity>
<h>1</h>
<k>1</k>
<l>4</l>
<F/>
</intensity>
<intensity>
<theta>34.425</theta>
<da>2.60304</da>
<intensity>109m</intensity>
<h>0</h>
<k>0</k>
<l>4</l>
<F/>
</intensity>
<intensity>
<theta>34.425</theta>
<da>2.60304</da>
<intensity>109m</intensity>
<h>2</h>
<k>-1</k>
<l>3</l>
<F/>
</intensity>
<intensity>
<theta>34.942</theta>
<da>2.56567</da>
<intensity>8</intensity>
<h>1</h>
<k>-2</k>
<l>3</l>
<F/>
</intensity>
<intensity>
<theta>35.045</theta>
<da>2.55841</da>
<intensity>10m</intensity>
<h>0</h>
<k>3</k>
<l>1</l>
<F/>
</intensity>
<intensity>
<theta>35.045</theta>
<da>2.55841</da>
<intensity>10m</intensity>
<h>0</h>
<k>-3</k>
<l>1</l>
<F/>
</intensity>
<intensity>
<theta>35.234</theta>
<da>2.54510</da>
<intensity>11m</intensity>
<h>1</h>
<k>3</k>
<l>0</l>
<F/>
</intensity>
<intensity>
<theta>35.234</theta>
<da>2.54510</da>
<intensity>11m</intensity>
<h>1</h>
<k>3</k>
<l>1</l>
<F/>
</intensity>
<intensity>
<theta>35.335</theta>
<da>2.53807</da>
<intensity>11</intensity>
<h>1</h>
<k>-1</k>
<l>4</l>
<F/>
</intensity>
<intensity>
<theta>36.301</theta>
<da>2.47271</da>
<intensity>11m</intensity>
<h>0</h>
<k>1</k>
<l>4</l>
<F/>
</intensity>
<intensity>
<theta>36.301</theta>
<da>2.47271</da>
<intensity>11m</intensity>
<h>0</h>
<k>-1</k>
<l>4</l>
<F/>
</intensity>
<intensity>
<theta>36.787</theta>
<da>2.44115</da>
<intensity>53m</intensity>
<h>-2</h>
<k>0</k>
<l>2</l>
<F/>
</intensity>
<intensity>
<theta>36.787</theta>
<da>2.44115</da>
<intensity>53m</intensity>
<h>-2</h>
<k>-2</k>
<l>1</l>
<F/>
</intensity>
<intensity>
<theta>36.993</theta>
<da>2.42801</da>
<intensity>35m</intensity>
<h>2</h>
<k>0</k>
<l>4</l>
<F/>
</intensity>
<intensity>
<theta>36.993</theta>
<da>2.42801</da>
<intensity>35m</intensity>
<h>2</h>
<k>2</k>
<l>3</l>
<F/>
</intensity>
<intensity>
<theta>37.368</theta>
<da>2.40448</da>
<intensity>17m</intensity>
<h>1</h>
<k>3</k>
<l>2</l>
<F/>
</intensity>
<intensity>
<theta>37.368</theta>
<da>2.40448</da>
<intensity>17m</intensity>
<h>-1</h>
<k>-3</k>
<l>1</l>
<F/>
</intensity>
<intensity>
<theta>37.672</theta>
<da>2.38578</da>
<intensity>36m</intensity>
<h>-2</h>
<k>2</k>
<l>0</l>
<F/>
</intensity>
<intensity>
<theta>37.672</theta>
<da>2.38578</da>
<intensity>36m</intensity>
<h>-2</h>
<k>-1</k>
<l>2</l>
<F/>
</intensity>
<intensity>
<theta>37.742</theta>
<da>2.38153</da>
<intensity>40m</intensity>
<h>2</h>
<k>1</k>
<l>4</l>
<F/>
</intensity>
<intensity>
<theta>37.742</theta>
<da>2.38153</da>
<intensity>40m</intensity>
<h>2</h>
<k>-2</k>
<l>2</l>
<F/>
</intensity>
<intensity>
<theta>38.201</theta>
<da>2.35399</da>
<intensity>51m</intensity>
<h>0</h>
<k>3</k>
<l>2</l>
<F/>
</intensity>
<intensity>
<theta>38.201</theta>
<da>2.35399</da>
<intensity>51m</intensity>
<h>0</h>
<k>-3</k>
<l>2</l>
<F/>
</intensity>
<intensity>
<theta>39.138</theta>
<da>2.29975</da>
<intensity>5</intensity>
<h>-1</h>
<k>-2</k>
<l>3</l>
<F/>
</intensity>
<intensity>
<theta>39.492</theta>
<da>2.27992</da>
<intensity>1</intensity>
<h>-2</h>
<k>1</k>
<l>2</l>
<F/>
</intensity>
<intensity>
<theta>39.690</theta>
<da>2.26903</da>
<intensity>2</intensity>
<h>2</h>
<k>-1</k>
<l>4</l>
<F/>
</intensity>
<intensity>
<theta>39.762</theta>
<da>2.26509</da>
<intensity>2m</intensity>
<h>3</h>
<k>0</k>
<l>1</l>
<F/>
</intensity>
<intensity>
<theta>39.762</theta>
<da>2.26509</da>
<intensity>2m</intensity>
<h>3</h>
<k>0</k>
<l>2</l>
<F/>
</intensity>
<intensity>
<theta>40.126</theta>
<da>2.24535</da>
<intensity>62m</intensity>
<h>1</h>
<k>-3</k>
<l>2</l>
<F/>
</intensity>
<intensity>
<theta>40.126</theta>
<da>2.24535</da>
<intensity>62m</intensity>
<h>3</h>
<k>1</k>
<l>2</l>
<F/>
</intensity>
<intensity>
<theta>40.648</theta>
<da>2.21772</da>
<intensity>4m</intensity>
<h>2</h>
<k>3</k>
<l>1</l>
<F/>
</intensity>
<intensity>
<theta>40.648</theta>
<da>2.21772</da>
<intensity>4m</intensity>
<h>-2</h>
<k>2</k>
<l>1</l>
<F/>
</intensity>
<intensity>
<theta>40.750</theta>
<da>2.21242</da>
<intensity>4</intensity>
<h>2</h>
<k>-2</k>
<l>3</l>
<F/>
</intensity>
<intensity>
<theta>40.957</theta>
<da>2.20172</da>
<intensity>4</intensity>
<h>-1</h>
<k>2</k>
<l>3</l>
<F/>
</intensity>
<intensity>
<theta>41.074</theta>
<da>2.19571</da>
<intensity>7m</intensity>
<h>1</h>
<k>-2</k>
<l>4</l>
<F/>
</intensity>
<intensity>
<theta>41.074</theta>
<da>2.19571</da>
<intensity>7m</intensity>
<h>-1</h>
<k>0</k>
<l>4</l>
<F/>
</intensity>
<intensity>
<theta>41.269</theta>
<da>2.18577</da>
<intensity>21m</intensity>
<h>1</h>
<k>0</k>
<l>5</l>
<F/>
</intensity>
<intensity>
<theta>41.269</theta>
<da>2.18577</da>
<intensity>21m</intensity>
<h>-1</h>
<k>-3</k>
<l>2</l>
<F/>
</intensity>
<intensity>
<theta>41.340</theta>
<da>2.18219</da>
<intensity>25</intensity>
<h>1</h>
<k>3</k>
<l>3</l>
<F/>
</intensity>
<intensity>
<theta>41.486</theta>
<da>2.17485</da>
<intensity>151m</intensity>
<h>0</h>
<k>2</k>
<l>4</l>
<F/>
</intensity>
<intensity>
<theta>41.486</theta>
<da>2.17485</da>
<intensity>151m</intensity>
<h>0</h>
<k>-2</k>
<l>4</l>
<F/>
</intensity>
<intensity>
<theta>41.786</theta>
<da>2.15991</da>
<intensity>14m</intensity>
<h>3</h>
<k>0</k>
<l>3</l>
<F/>
</intensity>
<intensity>
<theta>41.786</theta>
<da>2.15991</da>
<intensity>14m</intensity>
<h>-2</h>
<k>-2</k>
<l>2</l>
<F/>
</intensity>
<intensity>
<theta>41.966</theta>
<da>2.15108</da>
<intensity>45m</intensity>
<h>2</h>
<k>2</k>
<l>4</l>
<F/>
</intensity>
<intensity>
<theta>41.966</theta>
<da>2.15108</da>
<intensity>45m</intensity>
<h>3</h>
<k>1</k>
<l>0</l>
<F/>
</intensity>
<intensity>
<theta>42.276</theta>
<da>2.13600</da>
<intensity>29</intensity>
<h>-1</h>
<k>-1</k>
<l>4</l>
<F/>
</intensity>
<intensity>
<theta>42.743</theta>
<da>2.11376</da>
<intensity>7m</intensity>
<h>3</h>
<k>-1</k>
<l>1</l>
<F/>
</intensity>
<intensity>
<theta>42.743</theta>
<da>2.11376</da>
<intensity>7m</intensity>
<h>3</h>
<k>-1</k>
<l>2</l>
<F/>
</intensity>
<intensity>
<theta>43.012</theta>
<da>2.10114</da>
<intensity>8m</intensity>
<h>0</h>
<k>3</k>
<l>3</l>
<F/>
</intensity>
<intensity>
<theta>43.012</theta>
<da>2.10114</da>
<intensity>8m</intensity>
<h>0</h>
<k>-3</k>
<l>3</l>
<F/>
</intensity>
<intensity>
<theta>43.138</theta>
<da>2.09531</da>
<intensity>6</intensity>
<h>-1</h>
<k>1</k>
<l>4</l>
<F/>
</intensity>
<intensity>
<theta>43.278</theta>
<da>2.08885</da>
<intensity>2</intensity>
<h>1</h>
<k>-1</k>
<l>5</l>
<F/>
</intensity>
<intensity>
<theta>43.418</theta>
<da>2.08243</da>
<intensity>1</intensity>
<h>0</h>
<k>0</k>
<l>5</l>
<F/>
</intensity>
<intensity>
<theta>43.678</theta>
<da>2.07063</da>
<intensity>4m</intensity>
<h>3</h>
<k>2</k>
<l>1</l>
<F/>
</intensity>
<intensity>
<theta>43.678</theta>
<da>2.07063</da>
<intensity>4m</intensity>
<h>3</h>
<k>2</k>
<l>2</l>
<F/>
</intensity>
<intensity>
<theta>43.867</theta>
<da>2.06215</da>
<intensity>21m</intensity>
<h>1</h>
<k>-3</k>
<l>3</l>
<F/>
</intensity>
<intensity>
<theta>43.867</theta>
<da>2.06215</da>
<intensity>21m</intensity>
<h>-1</h>
<k>3</k>
<l>2</l>
<F/>
</intensity>
<intensity>
<theta>44.282</theta>
<da>2.04380</da>
<intensity>5m</intensity>
<h>-2</h>
<k>-1</k>
<l>3</l>
<F/>
</intensity>
<intensity>
<theta>44.282</theta>
<da>2.04380</da>
<intensity>5m</intensity>
<h>-2</h>
<k>-3</k>
<l>1</l>
<F/>
</intensity>
<intensity>
<theta>44.515</theta>
<da>2.03362</da>
<intensity>11m</intensity>
<h>2</h>
<k>1</k>
<l>5</l>
<F/>
</intensity>
<intensity>
<theta>44.515</theta>
<da>2.03362</da>
<intensity>11m</intensity>
<h>-3</h>
<k>1</k>
<l>0</l>
<F/>
</intensity>
<intensity>
<theta>44.976</theta>
<da>2.01385</da>
<intensity>2m</intensity>
<h>0</h>
<k>1</k>
<l>5</l>
<F/>
</intensity>
<intensity>
<theta>44.976</theta>
<da>2.01385</da>
<intensity>2m</intensity>
<h>0</h>
<k>-1</k>
<l>5</l>
<F/>
</intensity>
<intensity>
<theta>45.195</theta>
<da>2.00461</da>
<intensity>17m</intensity>
<h>-2</h>
<k>2</k>
<l>2</l>
<F/>
</intensity>
<intensity>
<theta>45.195</theta>
<da>2.00461</da>
<intensity>17m</intensity>
<h>-3</h>
<k>0</k>
<l>1</l>
<F/>
</intensity>
<intensity>
<theta>45.375</theta>
<da>1.99708</da>
<intensity>44m</intensity>
<h>2</h>
<k>-2</k>
<l>4</l>
<F/>
</intensity>
<intensity>
<theta>45.375</theta>
<da>1.99708</da>
<intensity>44m</intensity>
<h>3</h>
<k>2</k>
<l>0</l>
<F/>
</intensity>
<intensity>
<theta>45.528</theta>
<da>1.99070</da>
<intensity>7</intensity>
<h>-3</h>
<k>-1</k>
<l>1</l>
<F/>
</intensity>
<intensity>
<theta>45.798</theta>
<da>1.97960</da>
<intensity>94m</intensity>
<h>0</h>
<k>4</k>
<l>0</l>
<F/>
</intensity>
<intensity>
<theta>45.798</theta>
<da>1.97960</da>
<intensity>94m</intensity>
<h>2</h>
<k>-3</k>
<l>1</l>
<F/>
</intensity>
<intensity>
<theta>46.170</theta>
<da>1.96453</da>
<intensity>2</intensity>
<h>2</h>
<k>-1</k>
<l>5</l>
<F/>
</intensity>
<intensity>
<theta>46.401</theta>
<da>1.95528</da>
<intensity>3m</intensity>
<h>1</h>
<k>4</k>
<l>0</l>
<F/>
</intensity>
<intensity>
<theta>46.401</theta>
<da>1.95528</da>
<intensity>3m</intensity>
<h>1</h>
<k>4</k>
<l>1</l>
<F/>
</intensity>
<intensity>
<theta>46.677</theta>
<da>1.94434</da>
<intensity>22m</intensity>
<h>0</h>
<k>4</k>
<l>1</l>
<F/>
</intensity>
<intensity>
<theta>46.677</theta>
<da>1.94434</da>
<intensity>22m</intensity>
<h>-1</h>
<k>-3</k>
<l>3</l>
<F/>
</intensity>
<intensity>
<theta>46.767</theta>
<da>1.94082</da>
<intensity>10</intensity>
<h>1</h>
<k>3</k>
<l>4</l>
<F/>
</intensity>
<intensity>
<theta>48.157</theta>
<da>1.88801</da>
<intensity>10m</intensity>
<h>1</h>
<k>-2</k>
<l>5</l>
<F/>
</intensity>
<intensity>
<theta>48.157</theta>
<da>1.88801</da>
<intensity>10m</intensity>
<h>3</h>
<k>-1</k>
<l>4</l>
<F/>
</intensity>
<intensity>
<theta>48.605</theta>
<da>1.87163</da>
<intensity>17m</intensity>
<h>3</h>
<k>-2</k>
<l>2</l>
<F/>
</intensity>
<intensity>
<theta>48.605</theta>
<da>1.87163</da>
<intensity>17m</intensity>
<h>-2</h>
<k>-3</k>
<l>2</l>
<F/>
</intensity>
<intensity>
<theta>48.762</theta>
<da>1.86597</da>
<intensity>9m</intensity>
<h>2</h>
<k>3</k>
<l>4</l>
<F/>
</intensity>
<intensity>
<theta>48.762</theta>
<da>1.86597</da>
<intensity>9m</intensity>
<h>-3</h>
<k>-2</k>
<l>1</l>
<F/>
</intensity>
<intensity>
<theta>49.045</theta>
<da>1.85588</da>
<intensity>13m</intensity>
<h>3</h>
<k>2</k>
<l>4</l>
<F/>
</intensity>
<intensity>
<theta>49.045</theta>
<da>1.85588</da>
<intensity>13m</intensity>
<h>-1</h>
<k>3</k>
<l>3</l>
<F/>
</intensity>
<intensity>
<theta>49.121</theta>
<da>1.85319</da>
<intensity>15m</intensity>
<h>0</h>
<k>-3</k>
<l>4</l>
<F/>
</intensity>
<intensity>
<theta>49.121</theta>
<da>1.85319</da>
<intensity>15m</intensity>
<h>1</h>
<k>-3</k>
<l>4</l>
<F/>
</intensity>
<intensity>
<theta>49.205</theta>
<da>1.85022</da>
<intensity>14m</intensity>
<h>0</h>
<k>-4</k>
<l>2</l>
<F/>
</intensity>
<intensity>
<theta>49.205</theta>
<da>1.85022</da>
<intensity>14m</intensity>
<h>2</h>
<k>-3</k>
<l>3</l>
<F/>
</intensity>
<intensity>
<theta>49.405</theta>
<da>1.84319</da>
<intensity>1m</intensity>
<h>0</h>
<k>2</k>
<l>5</l>
<F/>
</intensity>
<intensity>
<theta>49.405</theta>
<da>1.84319</da>
<intensity>1m</intensity>
<h>0</h>
<k>-2</k>
<l>5</l>
<F/>
</intensity>
<intensity>
<theta>49.577</theta>
<da>1.83718</da>
<intensity>1m</intensity>
<h>1</h>
<k>-4</k>
<l>1</l>
<F/>
</intensity>
<intensity>
<theta>49.577</theta>
<da>1.83718</da>
<intensity>1m</intensity>
<h>-1</h>
<k>4</k>
<l>0</l>
<F/>
</intensity>
<intensity>
<theta>49.872</theta>
<da>1.82703</da>
<intensity>1m</intensity>
<h>3</h>
<k>3</k>
<l>1</l>
<F/>
</intensity>
<intensity>
<theta>49.872</theta>
<da>1.82703</da>
<intensity>1m</intensity>
<h>-1</h>
<k>0</k>
<l>5</l>
<F/>
</intensity>
<intensity>
<theta>50.023</theta>
<da>1.82184</da>
<intensity>1</intensity>
<h>1</h>
<k>0</k>
<l>6</l>
<F/>
</intensity>
<intensity>
<theta>50.284</theta>
<da>1.81301</da>
<intensity>2m</intensity>
<h>3</h>
<k>-2</k>
<l>3</l>
<F/>
</intensity>
<intensity>
<theta>50.284</theta>
<da>1.81301</da>
<intensity>2m</intensity>
<h>-3</h>
<k>0</k>
<l>2</l>
<F/>
</intensity>
<intensity>
<theta>50.549</theta>
<da>1.80412</da>
<intensity>13m</intensity>
<h>3</h>
<k>0</k>
<l>5</l>
<F/>
</intensity>
<intensity>
<theta>50.549</theta>
<da>1.80412</da>
<intensity>13m</intensity>
<h>-3</h>
<k>-1</k>
<l>2</l>
<F/>
</intensity>
<intensity>
<theta>50.827</theta>
<da>1.79492</da>
<intensity>5m</intensity>
<h>3</h>
<k>1</k>
<l>5</l>
<F/>
</intensity>
<intensity>
<theta>50.827</theta>
<da>1.79492</da>
<intensity>5m</intensity>
<h>-1</h>
<k>-1</k>
<l>5</l>
<F/>
</intensity>
<intensity>
<theta>51.045</theta>
<da>1.78774</da>
<intensity>14m</intensity>
<h>1</h>
<k>1</k>
<l>6</l>
<F/>
</intensity>
<intensity>
<theta>51.045</theta>
<da>1.78774</da>
<intensity>14m</intensity>
<h>-2</h>
<k>2</k>
<l>3</l>
<F/>
</intensity>
<intensity>
<theta>51.302</theta>
<da>1.77939</da>
<intensity>30m</intensity>
<h>2</h>
<k>4</k>
<l>0</l>
<F/>
</intensity>
<intensity>
<theta>51.302</theta>
<da>1.77939</da>
<intensity>30m</intensity>
<h>2</h>
<k>4</k>
<l>2</l>
<F/>
</intensity>
<intensity>
<theta>51.475</theta>
<da>1.77382</da>
<intensity>27m</intensity>
<h>2</h>
<k>0</k>
<l>6</l>
<F/>
</intensity>
<intensity>
<theta>51.475</theta>
<da>1.77382</da>
<intensity>27m</intensity>
<h>3</h>
<k>3</k>
<l>0</l>
<F/>
</intensity>
<intensity>
<theta>51.801</theta>
<da>1.76342</da>
<intensity>17m</intensity>
<h>1</h>
<k>-1</k>
<l>6</l>
<F/>
</intensity>
<intensity>
<theta>51.801</theta>
<da>1.76342</da>
<intensity>17m</intensity>
<h>-2</h>
<k>-1</k>
<l>4</l>
<F/>
</intensity>
<intensity>
<theta>52.106</theta>
<da>1.75383</da>
<intensity>1</intensity>
<h>2</h>
<k>1</k>
<l>6</l>
<F/>
</intensity>
<intensity>
<theta>52.793</theta>
<da>1.73260</da>
<intensity>40</intensity>
<h>-3</h>
<k>1</k>
<l>2</l>
<F/>
</intensity>
<intensity>
<theta>53.142</theta>
<da>1.72204</da>
<intensity>11m</intensity>
<h>3</h>
<k>-1</k>
<l>5</l>
<F/>
</intensity>
<intensity>
<theta>53.142</theta>
<da>1.72204</da>
<intensity>11m</intensity>
<h>-2</h>
<k>3</k>
<l>2</l>
<F/>
</intensity>
<intensity>
<theta>53.304</theta>
<da>1.71718</da>
<intensity>19m</intensity>
<h>1</h>
<k>3</k>
<l>5</l>
<F/>
</intensity>
<intensity>
<theta>53.304</theta>
<da>1.71718</da>
<intensity>19m</intensity>
<h>2</h>
<k>-3</k>
<l>4</l>
<F/>
</intensity>
<intensity>
<theta>53.615</theta>
<da>1.70795</da>
<intensity>114m</intensity>
<h>2</h>
<k>4</k>
<l>3</l>
<F/>
</intensity>
<intensity>
<theta>53.615</theta>
<da>1.70795</da>
<intensity>114m</intensity>
<h>4</h>
<k>0</k>
<l>2</l>
<F/>
</intensity>
<intensity>
<theta>54.051</theta>
<da>1.69520</da>
<intensity>6m</intensity>
<h>0</h>
<k>1</k>
<l>6</l>
<F/>
</intensity>
<intensity>
<theta>54.051</theta>
<da>1.69520</da>
<intensity>6m</intensity>
<h>0</h>
<k>-1</k>
<l>6</l>
<F/>
</intensity>
<intensity>
<theta>54.199</theta>
<da>1.69092</da>
<intensity>7m</intensity>
<h>4</h>
<k>1</k>
<l>1</l>
<F/>
</intensity>
<intensity>
<theta>54.199</theta>
<da>1.69092</da>
<intensity>7m</intensity>
<h>-2</h>
<k>-3</k>
<l>3</l>
<F/>
</intensity>
<intensity>
<theta>54.441</theta>
<da>1.68397</da>
<intensity>4m</intensity>
<h>2</h>
<k>3</k>
<l>5</l>
<F/>
</intensity>
<intensity>
<theta>54.441</theta>
<da>1.68397</da>
<intensity>4m</intensity>
<h>4</h>
<k>0</k>
<l>3</l>
<F/>
</intensity>
<intensity>
<theta>54.742</theta>
<da>1.67543</da>
<intensity>23m</intensity>
<h>1</h>
<k>2</k>
<l>6</l>
<F/>
</intensity>
<intensity>
<theta>54.742</theta>
<da>1.67543</da>
<intensity>23m</intensity>
<h>3</h>
<k>3</k>
<l>4</l>
<F/>
</intensity>
<intensity>
<theta>55.166</theta>
<da>1.66356</da>
<intensity>53</intensity>
<h>-2</h>
<k>-2</k>
<l>4</l>
<F/>
</intensity>
<intensity>
<theta>55.382</theta>
<da>1.65757</da>
<intensity>77m</intensity>
<h>2</h>
<k>2</k>
<l>6</l>
<F/>
</intensity>
<intensity>
<theta>55.382</theta>
<da>1.65757</da>
<intensity>77m</intensity>
<h>-1</h>
<k>3</k>
<l>4</l>
<F/>
</intensity>
<intensity>
<theta>56.048</theta>
<da>1.63946</da>
<intensity>6m</intensity>
<h>1</h>
<k>4</k>
<l>4</l>
<F/>
</intensity>
<intensity>
<theta>56.048</theta>
<da>1.63946</da>
<intensity>6m</intensity>
<h>4</h>
<k>2</k>
<l>2</l>
<F/>
</intensity>
<intensity>
<theta>56.189</theta>
<da>1.63567</da>
<intensity>9m</intensity>
<h>0</h>
<k>-3</k>
<l>5</l>
<F/>
</intensity>
<intensity>
<theta>56.189</theta>
<da>1.63567</da>
<intensity>9m</intensity>
<h>1</h>
<k>-2</k>
<l>6</l>
<F/>
</intensity>
<intensity>
<theta>56.374</theta>
<da>1.63074</da>
<intensity>2</intensity>
<h>4</h>
<k>-1</k>
<l>2</l>
<F/>
</intensity>
<intensity>
<theta>56.574</theta>
<da>1.62545</da>
<intensity>9m</intensity>
<h>4</h>
<k>0</k>
<l>0</l>
<F/>
</intensity>
<intensity>
<theta>56.574</theta>
<da>1.62545</da>
<intensity>9m</intensity>
<h>4</h>
<k>1</k>
<l>4</l>
<F/>
</intensity>
<intensity>
<theta>56.752</theta>
<da>1.62078</da>
<intensity>8m</intensity>
<h>3</h>
<k>0</k>
<l>6</l>
<F/>
</intensity>
<intensity>
<theta>56.752</theta>
<da>1.62078</da>
<intensity>8m</intensity>
<h>4</h>
<k>2</k>
<l>1</l>
<F/>
</intensity>
<intensity>
<theta>57.102</theta>
<da>1.61167</da>
<intensity>16m</intensity>
<h>2</h>
<k>-4</k>
<l>2</l>
<F/>
</intensity>
<intensity>
<theta>57.102</theta>
<da>1.61167</da>
<intensity>16m</intensity>
<h>3</h>
<k>1</k>
<l>6</l>
<F/>
</intensity>
<intensity>
<theta>57.384</theta>
<da>1.60440</da>
<intensity>23</intensity>
<h>-2</h>
<k>-4</k>
<l>2</l>
<F/>
</intensity>
<intensity>
<theta>57.522</theta>
<da>1.60089</da>
<intensity>15</intensity>
<h>2</h>
<k>4</k>
<l>4</l>
<F/>
</intensity>
<intensity>
<theta>57.974</theta>
<da>1.58949</da>
<intensity>38m</intensity>
<h>0</h>
<k>-2</k>
<l>6</l>
<F/>
</intensity>
<intensity>
<theta>57.974</theta>
<da>1.58949</da>
<intensity>38m</intensity>
<h>-2</h>
<k>2</k>
<l>4</l>
<F/>
</intensity>
<intensity>
<theta>58.225</theta>
<da>1.58323</da>
<intensity>39m</intensity>
<h>0</h>
<k>5</k>
<l>0</l>
<F/>
</intensity>
<intensity>
<theta>58.225</theta>
<da>1.58323</da>
<intensity>39m</intensity>
<h>2</h>
<k>-2</k>
<l>6</l>
<F/>
</intensity>
<intensity>
<theta>58.372</theta>
<da>1.57958</da>
<intensity>17m</intensity>
<h>1</h>
<k>5</k>
<l>0</l>
<F/>
</intensity>
<intensity>
<theta>58.372</theta>
<da>1.57958</da>
<intensity>17m</intensity>
<h>-2</h>
<k>3</k>
<l>3</l>
<F/>
</intensity>
<intensity>
<theta>58.536</theta>
<da>1.57555</da>
<intensity>18m</intensity>
<h>0</h>
<k>4</k>
<l>4</l>
<F/>
</intensity>
<intensity>
<theta>58.536</theta>
<da>1.57555</da>
<intensity>18m</intensity>
<h>0</h>
<k>-4</k>
<l>4</l>
<F/>
</intensity>
</stick_series>
</graphs>
</pdfcard>
